cookiebot/__init__.py
cookiebot/api.py
cookiebot/errors.py
cookiebot/models.py
cookiebot-0.2.0.dist-info/LICENSE
cookiebot-0.2.0.dist-info/METADATA
cookiebot-0.2.0.dist-info/WHEEL
cookiebot-0.2.0.dist-info/top_level.txt
cookiebot-0.2.0.dist-info/RECORD
