Metadata-Version: 2.1
Name: cookiebot
Version: 0.2.0
Summary: An API wrapper for the CookieBot API
Author: tibue99, tobfd
License: MIT
Project-URL: GitHub, https://github.com/tibue99/cookie-api
Project-URL: CookieBot, https://cookie-bot.xyz
Project-URL: Documentation, https://cookiebot.readthedocs.io
Keywords: cookie-bot,cookie,api
Classifier: Development Status :: 5 - Production/Stable
Classifier: License :: OSI Approved :: MIT License
Classifier: Intended Audience :: Developers
Classifier: Operating System :: OS Independent
Classifier: Programming Language :: Python :: 3.9
Classifier: Programming Language :: Python :: 3.10
Classifier: Programming Language :: Python :: 3.11
Classifier: Programming Language :: Python :: 3.12
Requires-Python: >=3.9
License-File: LICENSE
Requires-Dist: httpx
Requires-Dist: python-dotenv
